elphy/__init__.py
elphy/cli.py
elphy/elphy.py
elphy-0.1.0.dist-info/DESCRIPTION.rst
elphy-0.1.0.dist-info/METADATA
elphy-0.1.0.dist-info/RECORD
elphy-0.1.0.dist-info/WHEEL
elphy-0.1.0.dist-info/entry_points.txt
elphy-0.1.0.dist-info/metadata.json
elphy-0.1.0.dist-info/top_level.txt
