Metadata-Version: 2.0
Name: elphy
Version: 0.1.0
Summary: Material property estimation and analysis for magnetic resonance elastography (MRE) data.
Home-page: https://github.com/aaronta/elphy
Author: Aaron T Anderson
Author-email: aandrsn3@illinois.edu
License: MIT license
Keywords: elphy
Platform: UNKNOWN
Classifier: Development Status :: 2 - Pre-Alpha
Classifier: Intended Audience :: Developers
Classifier: License :: OSI Approved :: MIT License
Classifier: Natural Language :: English
Classifier: Programming Language :: Python :: 2
Classifier: Programming Language :: Python :: 2.7
Classifier: Programming Language :: Python :: 3
Classifier: Programming Language :: Python :: 3.4
Classifier: Programming Language :: Python :: 3.5
Classifier: Programming Language :: Python :: 3.6
Classifier: Programming Language :: Python :: 3.7
Requires-Dist: Click (>=6.0)
